fungi/__init__.py
fungi/__main__.py
fungi/fungi.py
fungi/manage.py
fungi_bot-0.1.1.dist-info/entry_points.txt
fungi_bot-0.1.1.dist-info/LICENSE
fungi_bot-0.1.1.dist-info/METADATA
fungi_bot-0.1.1.dist-info/WHEEL
fungi_bot-0.1.1.dist-info/RECORD
